[{"id":"c789455c.cc271","type":"ibmiot","z":"c7aada7a.6beb4","name":"coi0nz"},{"id":"f7cc4538.281908","type":"debug","z":"2c137dae.57f882","name":"Debug","active":false,"console":"false","complete":"payload","x":697,"y":453,"wires":[]},{"id":"e71e3625.9b1098","type":"ibmiot in","z":"2c137dae.57f882","authentication":"apiKey","apiKey":"c789455c.cc271","inputType":"evt","deviceId":"","applicationId":"","deviceType":"+","eventType":"+","commandType":"","format":"json","name":"Subscribe and print events in Debug Panel","service":"registered","allDevices":true,"allApplications":"","allDeviceTypes":true,"allEvents":true,"allCommands":"","allFormats":true,"x":405,"y":452.5,"wires":[["f7cc4538.281908"]]}]